pycep_correios/__init__.py
pycep_correios/apicep.py
pycep_correios/client.py
pycep_correios/correios.py
pycep_correios/exceptions.py
pycep_correios/viacep.py
pycep_correios-5.1.0.dist-info/LICENSE
pycep_correios-5.1.0.dist-info/METADATA
pycep_correios-5.1.0.dist-info/WHEEL
pycep_correios-5.1.0.dist-info/top_level.txt
pycep_correios-5.1.0.dist-info/RECORD
