Metadata-Version: 2.1
Name: pycep_correios
Version: 5.1.0
Summary: API para consulta de CEPs
Home-page: https://github.com/mstuttgart/pycep-correios
Author: Michell Stuttgart Faria
Author-email: michellstut@gmail.com
Maintainer: Michell Stuttgart Faria
Maintainer-email: michellstut@gmail.com
License: MIT License
Download-URL: https://github.com/mstuttgart/pycep-correios
Keywords: correios viacep apicep cep
Platform: UNKNOWN
Classifier: Development Status :: 5 - Production/Stable
Classifier: Intended Audience :: Developers
Classifier: Natural Language :: Portuguese
Classifier: License :: OSI Approved :: MIT License
Classifier: Programming Language :: Python :: 3.5
Classifier: Programming Language :: Python :: 3.6
Classifier: Programming Language :: Python :: 3.7
Classifier: Programming Language :: Python :: 3.8
